{
  "key": "lumen_session_2026_03_10",
  "title": "Lumen Session — 2026-03-10 (Planning & Architecture)",
  "content": "# Session Digest — 2026-03-10\n\n## What We Worked On\nLumen GM Hub project planning — from initial concept through PoC plan, architecture decisions, and vault documentation. This was a full strategic planning session, not a coding session.\n\n## Decisions Made\n\n### Strategic\n- Sylvara remains the #1 priority. Lumen is secondary. Failstate is back-burnered. [EXPLICIT]\n- Lumen is a standalone subscription product, not something to sell to Paizo. [EXPLICIT]\n- The \"build a mobile app for quick income\" idea was abandoned in favor of doubling down on existing projects. [EXPLICIT]\n\n### Architectural\n- **VoIP-first architecture** (ADR-001): built-in WebRTC voice client replaces Discord loopback + VB-Cable + pyannote. Speaker attribution is deterministic via per-stream capture.\n- **No Discord fallback** (ADR-002): maintaining two audio architectures isn't worth the complexity. If VoIP works, ship VoIP only.\n- **Electron for Hub** (ADR-003): bundles Chromium's WebRTC stack. Players use browser — no install.\n- **Two-tier business model** (ADR-004): local (free/cheap, GM's GPU) + cloud (premium, Lumen servers). Ship local first.\n- **faster-whisper over vanilla Whisper** (ADR-005): CTranslate2 backend for speed and VRAM efficiency.\n\n### Technical\n- pyannote removed entirely — per-stream capture eliminates the need for diarization. [EXPLICIT]\n- VB-Cable and WASAPI loopback removed — VoIP replaces them. [EXPLICIT]\n- `medium` Whisper model is the likely sweet spot for 8GB cards now that pyannote's VRAM is freed. [EXPLICIT]\n- `large-v3` becomes testable on 8GB cards. [EXPLICIT]\n- Signaling server is a thin cloud dependency — only for ICE negotiation, never touches audio. [EXPLICIT]\n\n## Facts Learned\n- Cole's GPU: RTX 3070 (8GB VRAM) [EXPLICIT]\n- Cole plays D&D/PF2e and uses Foundry VTT [EXPLICIT]\n- Cole is interested in Lumen as a potential income stream alongside Sylvara [EXPLICIT]\n- Cole values the VoIP approach because it simplifies the user experience and improves attribution [EXPLICIT]\n- Cole considered the third-party hosting (Ventrilo) model but was convinced the tiered model is better [EXPLICIT]\n- Cole is new to the Obsidian vault workflow — brain files are a new concept for him [EXPLICIT]\n- Cole's ADHD tendency to start new projects was self-identified — he came in asking about a 4th project before refocusing [EXPLICIT]\n\n## Open Threads\n- [ ] PoC Phase 1 — Whisper benchmarking on RTX 3070 (not started)\n- [ ] PoC Phase 2 — WebRTC VoIP client integration (not started)\n- [ ] PoC Phase 3 — Integrated pipeline + 60-min session test (not started)\n- [ ] PoC Phase 4 — Go/no-go verdict (not started)\n- [ ] Post-PoC: Cloud cost benchmark (deploy Whisper on cloud GPU, measure real cost)\n- [ ] Post-PoC: PF2e community survey (hardware, pricing tolerance, privacy attitudes)\n- [ ] Spec v3 may need updating as PoC produces real data — especially VRAM budget and spec tiers\n\n## Related Projects\n- Lumen GM Hub (primary focus of this session)\n- Sylvara (mentioned as priority context — no work done)\n- Failstate (mentioned as back-burnered — no work done)\n\n## Keywords\nlumen, voip, whisper, architecture, poc, planning, vault-setup\n\n\n---\n**2026-03-16T00:37:27.592174-07:00 | Created via Engram**",
  "tags": [
    "lumen",
    "journal",
    "session"
  ],
  "created_at": "2026-03-16T00:37:27.592174-07:00",
  "updated_at": "2026-03-16T00:37:27.592174-07:00",
  "chars": 3217,
  "lines": 55,
  "chunk_count": 10
}